setup.py
mongoforms_dfields/__init__.py
mongoforms_dfields/generator.py
mongoforms_dfields/models.py
mongoforms_dfields.egg-info/PKG-INFO
mongoforms_dfields.egg-info/SOURCES.txt
mongoforms_dfields.egg-info/dependency_links.txt
mongoforms_dfields.egg-info/not-zip-safe
mongoforms_dfields.egg-info/requires.txt
mongoforms_dfields.egg-info/top_level.txt