Metadata-Version: 1.1
Name: mongoforms-dfields
Version: 0.2.1
Summary: A ModelForm-DynamicFields
Home-page: https://github.com/multmeio/mongoforms_dfields
Author: Luís Araújo
Author-email: luis@multmeio.com.br
License: UNKNOWN
Platform: UNKNOWN
Classifier: Development Status :: 3 - Alpha
Classifier: Environment :: Web Environment
Classifier: Intended Audience :: Developers
Classifier: License :: OSI Approved :: BSD License
Classifier: Operating System :: OS Independent
Classifier: Programming Language :: Python
Classifier: Framework :: Django
